docs/__init__.py
docs/md_autogen.py
docs/update_docs.py
keras_vis-0.4.dist-info/DESCRIPTION.rst
keras_vis-0.4.dist-info/METADATA
keras_vis-0.4.dist-info/RECORD
keras_vis-0.4.dist-info/WHEEL
keras_vis-0.4.dist-info/metadata.json
keras_vis-0.4.dist-info/top_level.txt
vis/__init__.py
vis/backprop_modifiers.py
vis/callbacks.py
vis/grad_modifiers.py
vis/input_modifiers.py
vis/losses.py
vis/optimizer.py
vis/regularizers.py
vis/backend/__init__.py
vis/backend/tensorflow_backend.py
vis/backend/theano_backend.py
vis/utils/__init__.py
vis/utils/test_utils.py
vis/utils/utils.py
vis/visualization/__init__.py
vis/visualization/activation_maximization.py
vis/visualization/saliency.py
